aliyunsdkdypnsapi/__init__.py
aliyunsdkdypnsapi/endpoint.py
aliyunsdkdypnsapi/request/__init__.py
aliyunsdkdypnsapi/request/v20170525/CheckSmsVerifyCodeRequest.py
aliyunsdkdypnsapi/request/v20170525/CreateSchemeConfigRequest.py
aliyunsdkdypnsapi/request/v20170525/CreateVerifySchemeRequest.py
aliyunsdkdypnsapi/request/v20170525/DeleteVerifySchemeRequest.py
aliyunsdkdypnsapi/request/v20170525/DescribeVerifySchemeRequest.py
aliyunsdkdypnsapi/request/v20170525/GetAuthTokenRequest.py
aliyunsdkdypnsapi/request/v20170525/GetAuthorizationUrlRequest.py
aliyunsdkdypnsapi/request/v20170525/GetFusionAuthTokenRequest.py
aliyunsdkdypnsapi/request/v20170525/GetMobileRequest.py
aliyunsdkdypnsapi/request/v20170525/GetPhoneWithTokenRequest.py
aliyunsdkdypnsapi/request/v20170525/GetSmsAuthTokensRequest.py
aliyunsdkdypnsapi/request/v20170525/QueryGateVerifyBillingPublicRequest.py
aliyunsdkdypnsapi/request/v20170525/QueryGateVerifyStatisticPublicRequest.py
aliyunsdkdypnsapi/request/v20170525/QuerySendDetailsRequest.py
aliyunsdkdypnsapi/request/v20170525/SendSmsVerifyCodeRequest.py
aliyunsdkdypnsapi/request/v20170525/VerifyMobileRequest.py
aliyunsdkdypnsapi/request/v20170525/VerifyPhoneWithTokenRequest.py
aliyunsdkdypnsapi/request/v20170525/VerifySmsCodeRequest.py
aliyunsdkdypnsapi/request/v20170525/VerifyWithFusionAuthTokenRequest.py
aliyunsdkdypnsapi/request/v20170525/__init__.py
aliyun_python_sdk_dypnsapi-1.1.13.dist-info/LICENSE
aliyun_python_sdk_dypnsapi-1.1.13.dist-info/METADATA
aliyun_python_sdk_dypnsapi-1.1.13.dist-info/WHEEL
aliyun_python_sdk_dypnsapi-1.1.13.dist-info/top_level.txt
aliyun_python_sdk_dypnsapi-1.1.13.dist-info/RECORD
